LICENSE
MANIFEST.in
setup.py
m2up/MarkdownPP.py
m2up/Module.py
m2up/Processor.py
m2up/Transform.py
m2up/__init__.py
m2up/main.py
m2up.egg-info/PKG-INFO
m2up.egg-info/SOURCES.txt
m2up.egg-info/dependency_links.txt
m2up.egg-info/entry_points.txt
m2up.egg-info/requires.txt
m2up.egg-info/top_level.txt
m2up/Modules/Include.py
m2up/Modules/IncludeCode.py
m2up/Modules/IncludeURL.py
m2up/Modules/LaTeXRender.py
m2up/Modules/Reference.py
m2up/Modules/TableOfContents.py
m2up/Modules/YoutubeEmbed.py
m2up/Modules/__init__.py
test/test.py