Metadata-Version: 1.1
Name: m2up
Version: 1.0.2
Summary: Mark Markdown Up
Home-page: https://github.com/hailiang-wang/markdown-pp
Author: John Reese, Hai Liang W.
Author-email: hailiang.hl.wang@gmail.com
License: MIT License
Platform: UNKNOWN
Classifier: License :: OSI Approved :: MIT License
Classifier: Operating System :: OS Independent
Classifier: Programming Language :: Python
Classifier: Programming Language :: Python :: 2.7
Classifier: Programming Language :: Python :: 3
Classifier: Programming Language :: Python :: 3.4
Classifier: Programming Language :: Python :: 3.5
Classifier: Programming Language :: Python :: 3.6
Classifier: Topic :: Utilities
Classifier: Development Status :: 5 - Production/Stable
